colorfy/__init__.py
colorfy/colorfy.py
colorfy/palette.py
colorfy/stylist.py
colorfy_py-0.1.0.dist-info/LICENSE
colorfy_py-0.1.0.dist-info/METADATA
colorfy_py-0.1.0.dist-info/WHEEL
colorfy_py-0.1.0.dist-info/top_level.txt
colorfy_py-0.1.0.dist-info/RECORD
