Metadata-Version: 2.1
Name: colorfy-py
Version: 0.1.0
Summary: Library for text formatting in Unix-based systems
Author-email: CelestialEcho <borya.mishchenko2009@example.com>
License:                                  Apache License
Keywords: text-formatting,colors,Terminal,UNIX,coloring,colorama,Windows,color,Windows,formatting
Classifier: Development Status :: 3 - Alpha
Classifier: Intended Audience :: Developers
Classifier: Programming Language :: Python :: 3
Classifier: License :: OSI Approved :: Apache Software License
Classifier: Operating System :: OS Independent
Classifier: Topic :: Software Development :: Libraries
Classifier: Topic :: Text Processing
Requires-Python: >=3.7
License-File: LICENSE
